<?xml version="1.0" encoding="UTF-8"?>
<beans xmlns="http://www.springframework.org/schema/beans"
	xmlns:xsi="http://www.w3.org/2001/XMLSchema-instance"
	xmlns:mybatis-spring="http://mybatis.org/schema/mybatis-spring"
	xsi:schemaLocation="http://mybatis.org/schema/mybatis-spring http://mybatis.org/schema/mybatis-spring-1.2.xsd
		http://www.springframework.org/schema/beans https://www.springframework.org/schema/beans/spring-beans.xsd">
	
	<!-- Root Context: defines shared resources visible to all other web components -->
	<bean class="com.zaxxer.hikari.HikariConfig" id="hikariConfig">
		<property name="driverClassName" value="oracle.jdbc.OracleDriver"/>
		<property name="jdbcUrl" value="jdbc:oracle:thin:@localhost:1521:xe"/>
		<property name="username" value="oracle"/>
		<property name="password" value="oracle"/>
	</bean>
	
	<bean class="com.zaxxer.hikari.HikariDataSource" id="dataSource">
		<constructor-arg ref="hikariConfig"/>
	</bean>
	
	<bean id="sessionFactory" class="org.mybatis.spring.SqlSessionFactoryBean">
		<property name="dataSource" ref="dataSource"/>
		<!-- mybatis에서 사용할 파일의 경로 -->
		<property name="mapperLocations" value="classpath:/mappers/*Mapper.xml"/>
	</bean>
	
	<!-- 인스턴스로 지정 및 파일의 최대 사이즈 지정 -->
	<bean id="multipartResolver"
		class="org.springframework.web.multipart.commons.CommonsMultipartResolver">
		<property name="maxUploadSize" value="52428800" />
	</bean>
	
	<!-- mybatis-spring:scan : 태그를 사용하기 위하여 Namespaces를 등록 해야한다. -->
	<mybatis-spring:scan base-package="com.care.dbQuiz.repository"/>
	<mybatis-spring:scan base-package="com.care.dbQuiz.board"/>
</beans>
